env_to_vault/__init__.py
env_to_vault/cli.py
env_to_vault/config.py
env_to_vault/parser.py
env_to_vault/vault.py
env_to_vault-0.1.4.dist-info/METADATA
env_to_vault-0.1.4.dist-info/WHEEL
env_to_vault-0.1.4.dist-info/entry_points.txt
env_to_vault-0.1.4.dist-info/licenses/LICENSE
env_to_vault-0.1.4.dist-info/RECORD
