Metadata-Version: 2.4
Name: env-to-vault
Version: 0.1.4
Summary: A tool to convert environment variables from ENV files to HashiCorp Vault Secret Engine format
Author-email: Nadeshiko Manju <nadeshiko.manju@example.com>
License: MIT
License-File: LICENSE
Classifier: Development Status :: 3 - Alpha
Classifier: Intended Audience :: Developers
Classifier: License :: OSI Approved :: MIT License
Requires-Python: >=3.12
Requires-Dist: click>=8.0.0
Requires-Dist: hvac>=1.0.0
Requires-Dist: pydantic>=2.0.0
Requires-Dist: python-dotenv>=1.0.0
Requires-Dist: pyyaml>=6.0.0
Provides-Extra: dev
Requires-Dist: black>=23.0.0; extra == 'dev'
Requires-Dist: mypy>=1.0.0; extra == 'dev'
Requires-Dist: pytest-cov>=4.0.0; extra == 'dev'
Requires-Dist: pytest>=7.0.0; extra == 'dev'
